dehb/__init__.py
dehb/optimizers/__init__.py
dehb/optimizers/de.py
dehb/optimizers/dehb.py
dehb/utils/__init__.py
dehb/utils/bracket_manager.py
dehb/utils/config_repository.py
DEHB-0.1.2.dist-info/LICENSE.txt
DEHB-0.1.2.dist-info/METADATA
DEHB-0.1.2.dist-info/WHEEL
DEHB-0.1.2.dist-info/top_level.txt
DEHB-0.1.2.dist-info/RECORD
