Metadata-Version: 2.1
Name: DEHB
Version: 0.1.2
Summary: Evolutionary Hyperband for Scalable, Robust and Efficient Hyperparameter Optimization
Author: Noor Awad, Frank Hutter
Author-email: Neeratyoy Mallik <mallik@cs.uni-freiburg.de>, Janis Fix <fixj@cs.uni-freiburg.de>
License: Apache License
Project-URL: Documentation, https://automl.github.io/DEHB/
Project-URL: Github, https://github.com/automl/DEHB
Classifier: Programming Language :: Python :: 3.8
Classifier: Programming Language :: Python :: 3.9
Classifier: Programming Language :: Python :: 3.10
Classifier: Programming Language :: Python :: 3.11
Classifier: Natural Language :: English
Classifier: Intended Audience :: Developers
Classifier: Intended Audience :: Education
Classifier: Intended Audience :: Science/Research
Classifier: Topic :: Scientific/Engineering
Classifier: Topic :: Scientific/Engineering :: Artificial Intelligence
Requires-Python: >=3.8
License-File: LICENSE.txt
Requires-Dist: numpy <2.0,>=1.18.2
Requires-Dist: loguru >=0.5.3
Requires-Dist: dask >=2.27.0
Requires-Dist: distributed >=2.27.0
Requires-Dist: ConfigSpace >=0.4.16
Requires-Dist: pandas >=1.2.4
Requires-Dist: pyarrow >=16.1.0
Provides-Extra: benchmarking
Requires-Dist: matplotlib ; extra == 'benchmarking'
Requires-Dist: markdown-table-generator ; extra == 'benchmarking'
Provides-Extra: dev
Requires-Dist: pytest >=4.6 ; extra == 'dev'
Requires-Dist: pytest-cov ; extra == 'dev'
Requires-Dist: pytest-xdist ; extra == 'dev'
Requires-Dist: pytest-timeout ; extra == 'dev'
Requires-Dist: mkdocs ; extra == 'dev'
Requires-Dist: mkdocs-material ; extra == 'dev'
Requires-Dist: mkdocstrings[python] ; extra == 'dev'
Requires-Dist: markdown-exec[ansi] ; extra == 'dev'
Requires-Dist: mkdocs-jupyter ; extra == 'dev'
Requires-Dist: mike ; extra == 'dev'
Requires-Dist: ruff ; extra == 'dev'
Requires-Dist: black ; extra == 'dev'
Requires-Dist: pre-commit ; extra == 'dev'
Provides-Extra: examples
Requires-Dist: scikit-learn ; extra == 'examples'
Requires-Dist: matplotlib ; extra == 'examples'
Provides-Extra: hpobench_benchmark
Requires-Dist: scikit-learn ==0.23.2 ; extra == 'hpobench_benchmark'
Requires-Dist: numpy ==1.20.0 ; extra == 'hpobench_benchmark'
Requires-Dist: tqdm ; extra == 'hpobench_benchmark'
Requires-Dist: pandas ==1.2.4 ; extra == 'hpobench_benchmark'
Requires-Dist: openml ==0.12.2 ; extra == 'hpobench_benchmark'
Requires-Dist: ConfigSpace <0.7.1 ; extra == 'hpobench_benchmark'
Requires-Dist: pillow ==10.3.0 ; extra == 'hpobench_benchmark'
Provides-Extra: jahs_benchmark
Requires-Dist: typing-extensions ; extra == 'jahs_benchmark'
Requires-Dist: mf-prior-bench[jahs-bench] ==1.9.0 ; extra == 'jahs_benchmark'
Provides-Extra: pd1_benchmark
Requires-Dist: mf-prior-bench[pd1] ==1.9.0 ; extra == 'pd1_benchmark'
